{
	"$schema": "http://schema.management.azure.com/schemas/2015-01-01/deploymentTemplate.json#",
	"contentVersion": "1.0.0.0",
	"parameters": {
		"factoryName": {
			"type": "string",
			"metadata": "Data Factory name",
			"defaultValue": "rajamadf1"
		},
		"AmazonS31_secretAccessKey": {
			"type": "secureString",
			"metadata": "Secure string for 'secretAccessKey' of 'AmazonS31'"
		},
		"AzureBlobStorage1_connectionString": {
			"type": "secureString",
			"metadata": "Secure string for 'connectionString' of 'AzureBlobStorage1'"
		},
		"AmazonS31_properties_typeProperties_accessKeyId": {
			"type": "string",
			"defaultValue": "abc"
		}
	},
	"variables": {
		"factoryId": "[concat('Microsoft.DataFactory/factories/', parameters('factoryName'))]"
	},
	"resources": [
		{
			"name": "[concat(parameters('factoryName'), '/pipeline1')]",
			"type": "Microsoft.DataFactory/factories/pipelines",
			"apiVersion": "2018-06-01",
			"properties": {
				"activities": [
					{
						"name": "Set variable1",
						"type": "SetVariable",
						"dependsOn": [],
						"policy": {
							"secureOutput": false,
							"secureInput": false
						},
						"userProperties": [],
						"typeProperties": {
							"variableName": "variable1",
							"value": "1"
						}
					}
				],
				"policy": {
					"elapsedTimeMetric": {}
				},
				"variables": {
					"variable1": {
						"type": "String"
					}
				},
				"annotations": []
			},
			"dependsOn": []
		},
		{
			"name": "[concat(parameters('factoryName'), '/default')]",
			"type": "Microsoft.DataFactory/factories/managedVirtualNetworks",
			"apiVersion": "2018-06-01",
			"properties": {},
			"dependsOn": []
		},
		{
			"name": "[concat(parameters('factoryName'), '/AutoResolveIntegrationRuntime')]",
			"type": "Microsoft.DataFactory/factories/integrationRuntimes",
			"apiVersion": "2018-06-01",
			"properties": {
				"type": "Managed",
				"typeProperties": {
					"computeProperties": {
						"location": "AutoResolve",
						"dataFlowProperties": {
							"computeType": "General",
							"coreCount": 8,
							"timeToLive": 0
						}
					}
				},
				"managedVirtualNetwork": {
					"type": "ManagedVirtualNetworkReference",
					"referenceName": "default"
				}
			},
			"dependsOn": [
				"[concat(variables('factoryId'), '/managedVirtualNetworks/default')]"
			]
		},
		{
			"name": "[concat(parameters('factoryName'), '/AmazonS31')]",
			"type": "Microsoft.DataFactory/factories/linkedServices",
			"apiVersion": "2018-06-01",
			"properties": {
				"annotations": [],
				"type": "AmazonS3",
				"typeProperties": {
					"serviceUrl": "https://s3.amazonaws.com",
					"accessKeyId": "[parameters('AmazonS31_properties_typeProperties_accessKeyId')]",
					"secretAccessKey": {
						"type": "SecureString",
						"value": "[parameters('AmazonS31_secretAccessKey')]"
					},
					"authenticationType": "AccessKey"
				},
				"connectVia": {
					"referenceName": "AutoResolveIntegrationRuntime",
					"type": "IntegrationRuntimeReference"
				}
			},
			"dependsOn": [
				"[concat(variables('factoryId'), '/integrationRuntimes/AutoResolveIntegrationRuntime')]"
			]
		},
		{
			"name": "[concat(parameters('factoryName'), '/AzureBlobStorage1')]",
			"type": "Microsoft.DataFactory/factories/linkedServices",
			"apiVersion": "2018-06-01",
			"properties": {
				"annotations": [],
				"type": "AzureBlobStorage",
				"typeProperties": {
					"connectionString": "[parameters('AzureBlobStorage1_connectionString')]"
				},
				"connectVia": {
					"referenceName": "AutoResolveIntegrationRuntime",
					"type": "IntegrationRuntimeReference"
				}
			},
			"dependsOn": [
				"[concat(variables('factoryId'), '/integrationRuntimes/AutoResolveIntegrationRuntime')]"
			]
		},
		{
			"name": "[concat(parameters('factoryName'), '/Binary1')]",
			"type": "Microsoft.DataFactory/factories/datasets",
			"apiVersion": "2018-06-01",
			"properties": {
				"linkedServiceName": {
					"referenceName": "AmazonS31",
					"type": "LinkedServiceReference"
				},
				"annotations": [],
				"type": "Binary",
				"typeProperties": {
					"location": {
						"type": "AmazonS3Location",
						"bucketName": "b67",
						"fileName": "20231114_183657.jpg"
					}
				}
			},
			"dependsOn": [
				"[concat(variables('factoryId'), '/linkedServices/AmazonS31')]"
			]
		}
	]
}